{"id":"f176dd8c-d5ea-4a64-8f8f-f14cc724c150","timestamp":1767751266269,"matcher":{"static":{},"wildcard":{},"dynamic":{}},"prerendered":["/","/donate","/sha512","/chscht","/sha224","/md5","/rabbit","/sha1","/sha3","/sha384","/hmacsha224","/rc4","/sha256","/hmacripemd160","/hmacsha384","/hmacsha256","/tripledes","/hmacsha1","/encoder","/microsofttranslate","/ripemd160","/hmacmd5","/base64","/qrcode","/xrptools","/life","/rc4drop","/tetris","/pic2base64","/aes","/decodetx","/des","/qrcodereader","/tontools","/hex","/pbkdf2","/hmacsha512","/qrcodemul","/jsonformat","/adatools","/abidecoder","/contract_evm"]}